{
  "type": "Feature",
  "stac_version": "1.0.0",
  "id": "forest_inventory_basal_area_2009_300000_6700000",
  "properties": {
    "proj:epsg": 3067,
    "proj:geometry": {
      "type": "Polygon",
      "coordinates": [
        [
          [
            300000.0,
            6600000.0
          ],
          [
            400000.0,
            6600000.0
          ],
          [
            400000.0,
            6700000.0
          ],
          [
            300000.0,
            6700000.0
          ],
          [
            300000.0,
            6600000.0
          ]
        ]
      ]
    },
    "proj:bbox": [
      300000.0,
      6600000.0,
      400000.0,
      6700000.0
    ],
    "proj:shape": [
      10000,
      10000
    ],
    "proj:transform": [
      10.0,
      0.0,
      300000.0,
      0.0,
      -10.0,
      6700000.0,
      0.0,
      0.0,
      1.0
    ],
    "proj:projjson": {
      "$schema": "https://proj.org/schemas/v0.6/projjson.schema.json",
      "type": "ProjectedCRS",
      "name": "ETRS89 / TM35FIN(E,N)",
      "base_crs": {
        "name": "ETRS89",
        "datum": {
          "type": "GeodeticReferenceFrame",
          "name": "European Terrestrial Reference System 1989",
          "ellipsoid": {
            "name": "GRS 1980",
            "semi_major_axis": 6378137,
            "inverse_flattening": 298.257222101
          }
        },
        "coordinate_system": {
          "subtype": "ellipsoidal",
          "axis": [
            {
              "name": "Geodetic latitude",
              "abbreviation": "Lat",
              "direction": "north",
              "unit": "degree"
            },
            {
              "name": "Geodetic longitude",
              "abbreviation": "Lon",
              "direction": "east",
              "unit": "degree"
            }
          ]
        },
        "id": {
          "authority": "EPSG",
          "code": 4258
        }
      },
      "conversion": {
        "name": "UTM zone 35N",
        "method": {
          "name": "Transverse Mercator",
          "id": {
            "authority": "EPSG",
            "code": 9807
          }
        },
        "parameters": [
          {
            "name": "Latitude of natural origin",
            "value": 0,
            "unit": "degree",
            "id": {
              "authority": "EPSG",
              "code": 8801
            }
          },
          {
            "name": "Longitude of natural origin",
            "value": 27,
            "unit": "degree",
            "id": {
              "authority": "EPSG",
              "code": 8802
            }
          },
          {
            "name": "Scale factor at natural origin",
            "value": 0.9996,
            "unit": "unity",
            "id": {
              "authority": "EPSG",
              "code": 8805
            }
          },
          {
            "name": "False easting",
            "value": 500000,
            "unit": "metre",
            "id": {
              "authority": "EPSG",
              "code": 8806
            }
          },
          {
            "name": "False northing",
            "value": 0,
            "unit": "metre",
            "id": {
              "authority": "EPSG",
              "code": 8807
            }
          }
        ]
      },
      "coordinate_system": {
        "subtype": "Cartesian",
        "axis": [
          {
            "name": "Easting",
            "abbreviation": "",
            "direction": "east",
            "unit": "metre"
          },
          {
            "name": "Northing",
            "abbreviation": "",
            "direction": "north",
            "unit": "metre"
          }
        ]
      },
      "id": {
        "authority": "EPSG",
        "code": 3067
      }
    },
    "start_datetime": "2009-01-01T00:00:00Z",
    "end_datetime": "2009-12-31T00:00:00Z",
    "datetime": "2023-07-27T07:00:16.090927Z"
  },
  "geometry": {
    "type": "Polygon",
    "coordinates": [
      [
        [
          23.46739795936657,
          59.49062560058654
        ],
        [
          25.232234634270622,
          59.52640830558134
        ],
        [
          25.183728785678415,
          60.42389879708035
        ],
        [
          23.370658325626895,
          60.386806782324484
        ],
        [
          23.46739795936657,
          59.49062560058654
        ]
      ]
    ]
  },
  "links": [
    {
      "rel": "root",
      "href": "../../catalog.json",
      "type": "application/json"
    },
    {
      "rel": "collection",
      "href": "../collection.json",
      "type": "application/json",
      "title": "Forest inventory, basal area"
    },
    {
      "rel": "parent",
      "href": "../collection.json",
      "type": "application/json",
      "title": "Forest inventory, basal area"
    }
  ],
  "assets": {
    "COG": {
      "href": "https://vm0160.kaj.pouta.csc.fi/luke/MVMI/ppa/2009/mvmi-ppa_2009_300000_6700000.tif",
      "type": "image/tiff; application=geotiff; profile=cloud-optimized",
      "title": "COG",
      "gsd": 10,
      "proj:shape": [
        10000,
        10000
      ],
      "proj:transform": [
        10.0,
        0.0,
        300000.0,
        0.0,
        -10.0,
        6700000.0,
        0.0,
        0.0,
        1.0
      ],
      "roles": [
        "data"
      ]
    },
    "10m": {
      "href": "https://vm0160.kaj.pouta.csc.fi/luke/MVMI/ppa/2009/mvmi-ppa_2009_300000_6700000_10m.tif",
      "type": "image/tiff; application=geotiff",
      "title": "10m",
      "gsd": 10,
      "proj:shape": [
        10000,
        10000
      ],
      "proj:transform": [
        10.0,
        0.0,
        300000.0,
        0.0,
        -10.0,
        6700000.0,
        0.0,
        0.0,
        1.0
      ],
      "roles": [
        "data"
      ]
    },
    "20m": {
      "href": "https://vm0160.kaj.pouta.csc.fi/luke/MVMI/ppa/2009/mvmi-ppa_2009_300000_6700000_20m.tif",
      "type": "image/tiff; application=geotiff",
      "title": "20m",
      "gsd": 20,
      "proj:shape": [
        5000,
        5000
      ],
      "proj:transform": [
        20.0,
        0.0,
        300000.0,
        0.0,
        -20.0,
        6700000.0,
        0.0,
        0.0,
        1.0
      ],
      "roles": [
        "data"
      ]
    },
    "50m": {
      "href": "https://vm0160.kaj.pouta.csc.fi/luke/MVMI/ppa/2009/mvmi-ppa_2009_300000_6700000_50m.tif",
      "type": "image/tiff; application=geotiff",
      "title": "50m",
      "gsd": 50,
      "proj:shape": [
        2000,
        2000
      ],
      "proj:transform": [
        50.0,
        0.0,
        300000.0,
        0.0,
        -50.0,
        6700000.0,
        0.0,
        0.0,
        1.0
      ],
      "roles": [
        "data"
      ]
    },
    "100m": {
      "href": "https://vm0160.kaj.pouta.csc.fi/luke/MVMI/ppa/2009/mvmi-ppa_2009_300000_6700000_100m.tif",
      "type": "image/tiff; application=geotiff",
      "title": "100m",
      "gsd": 100,
      "proj:shape": [
        1000,
        1000
      ],
      "proj:transform": [
        100.0,
        0.0,
        300000.0,
        0.0,
        -100.0,
        6700000.0,
        0.0,
        0.0,
        1.0
      ],
      "roles": [
        "data"
      ]
    },
    "200m": {
      "href": "https://vm0160.kaj.pouta.csc.fi/luke/MVMI/ppa/2009/mvmi-ppa_2009_300000_6700000_200m.tif",
      "type": "image/tiff; application=geotiff",
      "title": "200m",
      "gsd": 200,
      "proj:shape": [
        500,
        500
      ],
      "proj:transform": [
        200.0,
        0.0,
        300000.0,
        0.0,
        -200.0,
        6700000.0,
        0.0,
        0.0,
        1.0
      ],
      "roles": [
        "data"
      ]
    },
    "500m": {
      "href": "https://vm0160.kaj.pouta.csc.fi/luke/MVMI/ppa/2009/mvmi-ppa_2009_300000_6700000_500m.tif",
      "type": "image/tiff; application=geotiff",
      "title": "500m",
      "gsd": 500,
      "proj:shape": [
        200,
        200
      ],
      "proj:transform": [
        500.0,
        0.0,
        300000.0,
        0.0,
        -500.0,
        6700000.0,
        0.0,
        0.0,
        1.0
      ],
      "roles": [
        "data"
      ]
    },
    "1000m": {
      "href": "https://vm0160.kaj.pouta.csc.fi/luke/MVMI/ppa/2009/mvmi-ppa_2009_300000_6700000_1000m.tif",
      "type": "image/tiff; application=geotiff",
      "title": "1000m",
      "gsd": 1000,
      "proj:shape": [
        100,
        100
      ],
      "proj:transform": [
        1000.0,
        0.0,
        300000.0,
        0.0,
        -1000.0,
        6700000.0,
        0.0,
        0.0,
        1.0
      ],
      "roles": [
        "data"
      ]
    }
  },
  "bbox": [
    23.370658325626895,
    59.49062560058654,
    25.232234634270622,
    60.42389879708035
  ],
  "stac_extensions": [
    "https://stac-extensions.github.io/projection/v1.0.0/schema.json"
  ],
  "collection": "forest_inventory_basal_area_at_geocubes",
  "gsd": 10
}